{
    "prescriptions": [
        {
            "script_name": "Erythromycin 250 MG Delayed Release Oral Capsule [Eryc]",
            "dose":"1",
            "frequency1":"07:00:00",
            "frequency1": "15:00:00",
            "frequency2": null,
            "frequency3": null,
            "frequency4": null,
            "frequency5": null,
            "frequency6": null,
            "exp_date":"5/29/2018",
            "date_entered":"11/1/2017",
            "total_in_bottle":"30",
            "patient_id":"1",
            "doctor_name":"Marcus Aurelius",
            "pharmacy_name":"WalMart Pharmacy",
            "pharmacy_phone":"615-435-2446"
        },
        {
            "script_name": "metaxalone 400 MG Oral Tablet [Skelaxin]",
            "dose": "1",
            "frequency1": "07:00:00",
            "frequency1": "16:00:00",
            "frequency2": "23:00:00",
            "frequency3": null,
            "frequency4": null,
            "frequency5": null,
            "frequency6": null,
            "exp_date": "04/18/2018",
            "date_entered": "10/31/2017",
            "total_in_bottle": "60",
            "patient_id": "2",
            "doctor_name": "Theodora Byzantium",
            "pharmacy_name": "Walgreens",
            "pharmacy_phone": "615-302-1048"
        },
        {
            "script_name": "Cephalexin 250 MG Oral Capsule [Keflex]",
            "dose": "1",
            "frequency1": "07:00:00",
            "frequency2": "11:00:00",
            "frequency3": "18:00:00",
            "frequency4": "23:00:00",
            "frequency5": null,
            "frequency6": null,
            "exp_date": "01/23/2018",
            "date_entered": "10/29/2017",
            "total_in_bottle": "30",
            "patient_id": "3",
            "doctor_name": "Romulus Augustulus",
            "pharmacy_name": "CVS Pharmacy",
            "pharmacy_phone": "615-791-0974"
        },
        {
            "script_name": "Levothyroxine Sodium 0.137 MG Oral Tablet [Synthroid]",
            "dose": "1",
            "frequency1": "23:00:00",
            "frequency2": null,
            "frequency3": null,
            "frequency4": null,
            "frequency5": null,
            "frequency6": null,
            "exp_date": "01/20/2018",
            "date_entered": "11/1/2017",
            "total_in_bottle": "60",
            "patient_id": "3",
            "doctor_name": "Livia Augusta",
            "pharmacy_name": "Walgreens",
            "pharmacy_phone": "615-302-1048"
        },
        {
            "script_name": "24 HR tramadol hydrochloride 100 MG Extended Release Oral Tablet [Ultram]",
            "dose": "1",
            "frequency1": "06:00:00",
            "frequency2": "10:00:00",
            "frequency3": "14:00:00",
            "frequency4": "18:00:00",
            "frequency5": "22:00:00",
            "frequency6": "02:00:00",
            "exp_date": "01/10/2018",
            "date_entered": "11/1/2017",
            "total_in_bottle": "80",
            "patient_id": "3",
            "doctor_name": "Julia Domina",
            "pharmacy_name": "CVS Pharmacy",
            "pharmacy_phone": "615-791-0974"
        }
    ]
}